django_make
