Metadata-Version: 1.1
Name: django-make
Version: 0.0.3
Summary: Django development environment `$ make` middleware
Home-page: https://github.com/kelonye/django-make
Author: Mitchel Kelonye
Author-email: kelonyemitchel@gmail.com
License: MIT License
Platform: UNKNOWN
Requires: Django (>=1.3.0)
